{
  "title": "/all/ - All 5chan Directories",
  "description": "Each 5chan directory is assigned to a board handpicked by the team, until DAO curation is implemented.\n\nhttps://github.com/bitsocialhq/lists/blob/master/5chan-directories.json",
  "createdAt": 1762179811,
  "updatedAt": 1771140295,
  "directories": [
    {
      "title": "/pol/ - Politically Incorrect",
      "directoryCode": "pol",
      "communityAddress": "politically-incorrect.eth",
      "nsfw": true,
      "pseudonymityMode": "per-reply",
      "hasFlags": true
    },
    {
      "title": "/biz/ - Business & Finance",
      "directoryCode": "biz",
      "communityAddress": "business-and-finance.eth",
      "nsfw": false,
      "pseudonymityMode": "per-post",
      "hasFlags": false
    },
    {
      "title": "/sci/ - Science & Math",
      "directoryCode": "sci",
      "communityAddress": "science-and-math.eth",
      "nsfw": false,
      "pseudonymityMode": "per-reply",
      "hasFlags": false
    },
    {
      "title": "/g/ - Technology",
      "directoryCode": "g",
      "communityAddress": "technology-posting.eth",
      "nsfw": false,
      "pseudonymityMode": "per-reply",
      "hasFlags": false
    },
    {
      "title": "/vg/ - Video Game Generals",
      "directoryCode": "vg",
      "communityAddress": "videogame-generals.eth",
      "nsfw": false,
      "pseudonymityMode": "per-reply",
      "hasFlags": false
    },
    {
      "title": "/fit/ - Fitness",
      "directoryCode": "fit",
      "communityAddress": "fitness-posting.eth",
      "nsfw": false,
      "pseudonymityMode": "per-reply",
      "hasFlags": false
    },
    {
      "title": "/adv/ - Advice",
      "directoryCode": "adv",
      "communityAddress": "advice-posting.eth",
      "nsfw": false,
      "pseudonymityMode": "per-reply",
      "hasFlags": false
    },
    {
      "title": "/wsg/ - Worksafe GIF",
      "directoryCode": "wsg",
      "communityAddress": "worksafe-gif.eth",
      "nsfw": false,
      "pseudonymityMode": "per-reply",
      "hasFlags": false
    },
    {
      "title": "/diy/ - Do It Yourself",
      "directoryCode": "diy",
      "communityAddress": "do-it-yourself.eth",
      "nsfw": false,
      "pseudonymityMode": "per-reply",
      "hasFlags": false
    },
    {
      "title": "/out/ - Outdoors",
      "directoryCode": "out",
      "communityAddress": "outdoors-posting.eth",
      "nsfw": false,
      "pseudonymityMode": "per-reply",
      "hasFlags": false
    },
    {
      "title": "/ic/ - Artwork/Critique",
      "directoryCode": "ic",
      "communityAddress": "artwork-critique.eth",
      "nsfw": false,
      "pseudonymityMode": "per-reply",
      "hasFlags": false
    },
    {
      "title": "/mu/ - Music",
      "directoryCode": "mu",
      "communityAddress": "music-posting.eth",
      "nsfw": false,
      "pseudonymityMode": "per-reply",
      "hasFlags": false
    },
    {
      "title": "/int/ - International",
      "directoryCode": "int",
      "communityAddress": "international-sfw.eth",
      "nsfw": false,
      "pseudonymityMode": "per-reply",
      "hasFlags": true
    },
    {
      "title": "/lit/ - Literature",
      "directoryCode": "lit",
      "communityAddress": "literature-posting.eth",
      "nsfw": false,
      "pseudonymityMode": "per-reply",
      "hasFlags": false
    },
    {
      "title": "/tv/ - Television & Film",
      "directoryCode": "tv",
      "communityAddress": "television-and-film.eth",
      "nsfw": false,
      "pseudonymityMode": "per-reply",
      "hasFlags": false
    },
    {
      "title": "/vip/ - Very Important Posts",
      "directoryCode": "vip",
      "communityAddress": "very-important-posts.eth",
      "nsfw": false,
      "pseudonymityMode": "per-reply",
      "hasFlags": false
    },
    {
      "title": "/gif/ - Adult GIF",
      "directoryCode": "gif",
      "communityAddress": "adult-gif.eth",
      "nsfw": true,
      "pseudonymityMode": "per-reply",
      "hasFlags": false
    },
    {
      "title": "/bant/ - International/Random",
      "directoryCode": "bant",
      "communityAddress": "international-nsfw.eth",
      "nsfw": true,
      "pseudonymityMode": "per-post",
      "hasFlags": true
    },
    {
      "title": "/b/ - Random",
      "directoryCode": "b",
      "communityAddress": "random-nsfw.eth",
      "nsfw": true,
      "pseudonymityMode": "per-reply",
      "hasFlags": false
    }
  ]
}
